stats_library/__init__.py
stats_library/stats_descriptives.py
stats_descriptives_001-0.0.1.dist-info/LICENSE
stats_descriptives_001-0.0.1.dist-info/METADATA
stats_descriptives_001-0.0.1.dist-info/WHEEL
stats_descriptives_001-0.0.1.dist-info/top_level.txt
stats_descriptives_001-0.0.1.dist-info/RECORD
