Metadata-Version: 2.1
Name: stats-descriptives-001
Version: 0.0.1
Summary: Stats Descriptives including frequencies, descriptives, and crosstabs for easy export in xlsx
Author: Elisabeth Jones
Author-email: <ejones@rescueagency.com>
Classifier: Development Status :: 1 - Planning
Classifier: Intended Audience :: Developers
Classifier: Programming Language :: Python :: 3
Classifier: Operating System :: Unix
Classifier: Operating System :: MacOS :: MacOS X
Classifier: Operating System :: Microsoft :: Windows
License-File: LICENSE
Requires-Dist: pandas
Requires-Dist: numpy
